CHANGELOG.rst
LICENSE.txt
MANIFEST.in
README.rst
VERSION.txt
process.txt
setup.cfg
setup.py
secpass/__init__.py
secpass/api.py
secpass/engine.py
secpass/model.py
secpass/test_engine.py
secpass/test_helpers.py
secpass/util.py
secpass/cli/__init__.py
secpass/cli/base.py
secpass/cli/config.py
secpass/cli/note.py
secpass/cli/pass.py
secpass/cli/test_base.py
secpass/cli/test_config.py
secpass/driver/__init__.py
secpass/driver/file.py
secpass/driver/pgpfile.py
secpass/driver/spbp.py
secpass/driver/stream.py
secpass/driver/test_file.py
secpass/driver/test_pgpfile.py
secpass/driver/test_stream.py
secpass_gui/__init__.py
secpass_gui/main.py
secpass_gui.egg-info/PKG-INFO
secpass_gui.egg-info/SOURCES.txt
secpass_gui.egg-info/dependency_links.txt
secpass_gui.egg-info/entry_points.txt
secpass_gui.egg-info/not-zip-safe
secpass_gui.egg-info/requires.txt
secpass_gui.egg-info/top_level.txt