Metadata-Version: 1.1
Name: secpass-gui
Version: 0.1.0
Summary: Secure Passwords GUI
Home-page: http://github.com/metagriffin/secpass-gui
Author: metagriffin
Author-email: mg.pypi@metagriffin.net
License: GPLv3+
Keywords: secure password manager gui
Platform: any
Classifier: Development Status :: 2 - Pre-Alpha
Classifier: Environment :: X11 Applications
Classifier: Environment :: Win32 (MS Windows)
Classifier: Environment :: MacOS X
Classifier: Natural Language :: English
Classifier: Operating System :: OS Independent
Classifier: Programming Language :: Python
Classifier: Intended Audience :: End Users/Desktop
Classifier: Topic :: Utilities
Classifier: Topic :: Security
Classifier: License :: OSI Approved :: GNU General Public License v3 or later (GPLv3+)
